galib/__init__.py
galib/extra.py
galib/metrics.py
galib/metrics_numba.py
galib/models.py
galib/models_numba.py
galib/tools.py
galib-2.0.dist-info/METADATA
galib-2.0.dist-info/WHEEL
galib-2.0.dist-info/licenses/LICENSE.txt
galib-2.0.dist-info/RECORD
