Metadata-Version: 2.4
Name: galib
Version: 2.0
Summary: A library for graph analysis in Python / NumPy.
Project-URL: Homepage, https://github.com/gorkazl/pyGAlib
Project-URL: Source Code, https://github.com/gorkazl/pyGAlib/tree/master/src/galib
Project-URL: Bug Tracker, https://github.com/gorkazl/pyGAlib/issues
Project-URL: Documentation, https://github.com/gorkazl/pyGAlib/blob/master/README.md
Author-email: Gorka Zamora-López <gorka@Zamora-Lopez.xyz>
License-Expression: Apache-2.0
License-File: LICENSE.txt
Keywords: complex networks,graph theory,network analysis
Classifier: Development Status :: 5 - Production/Stable
Classifier: Intended Audience :: Developers
Classifier: Intended Audience :: Education
Classifier: Intended Audience :: Science/Research
Classifier: License :: OSI Approved :: Apache Software License
Classifier: Operating System :: OS Independent
Classifier: Programming Language :: Python
Classifier: Programming Language :: Python :: 3
Classifier: Topic :: Scientific/Engineering :: Bio-Informatics
Classifier: Topic :: Scientific/Engineering :: Information Analysis
Classifier: Topic :: Scientific/Engineering :: Mathematics
Classifier: Topic :: Scientific/Engineering :: Physics
Classifier: Topic :: Software Development :: Libraries :: Python Modules
Requires-Dist: numba
Requires-Dist: numpy>=1.6
Requires-Dist: scipy
